LICENSE
MANIFEST.in
README.rst
setup.cfg
setup.py
portal_core/__init__.py
portal_core/admin.py
portal_core/apps.py
portal_core/forms.py
portal_core/mixins.py
portal_core/models.py
portal_core/validators.py
portal_core.egg-info/PKG-INFO
portal_core.egg-info/SOURCES.txt
portal_core.egg-info/dependency_links.txt
portal_core.egg-info/not-zip-safe
portal_core.egg-info/requires.txt
portal_core.egg-info/top_level.txt
portal_core/utils/__init__.py
portal_core/utils/bank.py
portal_core/utils/datetime.py
portal_core/utils/gitlabapi.py
portal_core/utils/text_tools.py
portal_core/utils/upload.py